[
  {
    "name": "Font page",
    "icon": "homepage_fill",
    "base": "",
    "url": "home.html"
  },
  {
    "name": "Enter",
    "icon": "flashlight_fill",
    "base": "pages/inlet/",
    "subNav": [
      {
        "name": "Phase setting",
        "url": "inlet_set.html"
      },
      {
        "name": "Loop setting",
        "url": "loop_set.html"
      }
    ]
  },
  {
    "name": "Output",
    "icon": "subtraction",
    "base": "pages/outlet/",
    "subNav": [ 
      {
        "name": "Unit monitoring",
        "url": "output_monitoring.html"
      },
      {
        "name": "Unit current",
        "url": "outlet_cur.html"
      },
      {
        "name": "Unit power",
        "url": "outlet_pow.html"
      },  
      {
        "name": "Unit name",
        "url": "output_name.html"
      }, 
      {
        "name": "Unit control",
        "url": "relay_ctrl.html"
      },
      {
        "name": "Unit timing",
        "url": "relay_timing.html"
      },
      {
        "name": "Overrun power cut",
        "url": "overrun.html"
      },
      {
        "name": "Power reset",
        "url": "energe_clr.html"
      }     
    ]
  },
  {
    "name": "Group",
    "icon": "tasklist_fill",
    "base": "pages/group/",
    "subNav": [
      {
        "name": "Group setting",
        "url": "group_set.html"
      },
      {
        "name": "Group monitoring",
        "url": "group_monitoring.html"
      },
      {
        "name": "Group threshold",
        "url": "group_alarm.html"
      },
      {
        "name": "Group name",
        "url": "group_name.html"
      },
      {
        "name": "Group timing",
        "url": "group_timing.html"
      },
      {
        "name": "Group control",
        "url": "group_ctrl.html"
      } 
    ]
  }, 
  {
    "name": "Frame",
    "icon": "createtask_fill",
    "base": "pages/dual/",
    "subNav": [
      {
        "name": "Frame monitoring",
        "url": "dual_monitoring.html"
      },
      {
        "name": "Frame power",
        "url": "dual_pow.html"
      },
      {
        "name": "Frame name",
        "url": "dual_name.html"
      }     
    ]
  },
  {
    "name": "Environmental parameters",
    "icon": "flag_fill",
    "base": "",
    "url": "pages/envir/envir_ctrl.html"
  },
  {
    "name": "Device setting",
    "icon": "info",
    "base": "pages/devset/",
    "subNav": [
      {
        "name": "Mode setting",
        "url": "mode_set.html"
      },
      {
        "name": "Location setting",
        "url": "place_set.html"
      }         
    ]
  },
  {
    "name": "Integrated interface",
    "icon": "collection_fill",
    "base": "pages/integrate/",
    "subNav": [
      {
        "name": "Active push",
        "url": "push.html"
      },
      {
        "name": "RPC integration",
        "url": "rpc.html"
      },
      {
        "name": "REST integration",
        "url": "rest.html"
      },
      {
        "name": "MQTT integration",
        "url": "mqtt.html"
      },
      {
        "name": "AMQP service",
        "url": "amqp.html"
      },
      {
        "name": "SNMP service",
        "url": "snmp.html"
      },
      {
        "name": "Database service",
        "url": "odbc.html"
      },      
      {
        "name": "Modbus protocol",
        "url": "modbus.html"
      }
    ]
  }, 
  {
    "name": "Secure encryption",
    "icon": "lock_fill",
    "base": "pages/sercet/",
    "subNav": [      
      {
        "name": "Data encryption",
        "url": "data.html"
      },
      {
        "name": "TLS certificate",
        "url": "tlscert.html"
      },
      {
        "name": "Cyber security",
        "url": "net.html"
      },
      {
        "name": "Login Security",
        "url": "login_security.html"
      }
    ]
  },
  {
    "name": "Internet service",
    "icon": "computer_fill",
    "base": "pages/network/",
    "subNav": [
      {
        "name": "Internet connection",
        "url": "base.html"
      },
      {
        "name": "WEB service",
        "url": "web.html"
      },
      {
        "name": "NTP service",
        "url": "ntp.html"
      },
      {
        "name": "SSH service",
        "url": "ssh.html"
      },
      {
        "name": "SMTP service",
        "url": "smtp.html"
      },
      {
        "name": "Syslog service",
        "url": "syslog.html"
      },
      {
        "name": "Remote authentication service",
        "url": "radius.html"
      }
      
    ]
  },  
  {
    "name": "Chart information",
    "icon": "dynamic_fill",
    "base": "",
    "url": "pages/chart/chart.html"
  },
  {
    "name": "Log query",
    "icon": "document_fill",
    "base": "pages/logs/",
    "subNav": [
      {
        "name": "Alarm log",
        "url": "alarm_log.html"
      },
      {
        "name": "Event log",
        "url": "event_log.html"
      },
      {
        "name": "Historical data",
        "url": "history.html"
      },
      {
        "name": "Log setting",
        "url": "log_setting.html"
      }
    ]
  },
  {
    "name": "System maintenance",
    "icon": "manage_fill",
    "base": "pages/maintain/",
    "subNav": [
      {
        "name": "System information",
        "url": "sys_info.html"
      },
      {
        "name": "User information",
        "url": "usr_info.html"
      },
      {
        "name": "Update firmware",
        "url": "fw_update.html"
      },
      {
        "name": "Firmware history",
        "url": "fw_history.html"
      },
      {
        "name": "Batch configuration",
        "url": "batch_setting.html"
      },
      {
        "name": "Network diagnosis",
        "url": "net_diagnostics.html"
      },
      {
        "name": "Script Service",
        "url": "shell.html"
      },
      {
        "name": "Backup/Restore",
        "url": "backups.html"
      },
      {
        "name": "Download diagnosis",
        "url": "download_diagnosis.html"
      },
      {
        "name": "System command",
        "url": "sys_command.html"
      }
    ]
  }

]